marzpy/__init__.py
marzpy/marzban.py
marzpy/api/__init__.py
marzpy/api/admin.py
marzpy/api/core.py
marzpy/api/node.py
marzpy/api/send_requests.py
marzpy/api/subscription.py
marzpy/api/system.py
marzpy/api/template.py
marzpy/api/user.py
kodzmarzpy-0.0.2.dist-info/LICENSE
kodzmarzpy-0.0.2.dist-info/METADATA
kodzmarzpy-0.0.2.dist-info/WHEEL
kodzmarzpy-0.0.2.dist-info/top_level.txt
kodzmarzpy-0.0.2.dist-info/RECORD
