Metadata-Version: 2.1
Name: kodzmarzpy
Version: 0.0.2
Summary: A simple application with python to manage Marzban panel
Home-page: https://github.com/Kodzima34/marzpy
Author: Mewhrzad
Keywords: marzpy,Marzban,Gozargah,Marzban python,Marzban API
Classifier: Programming Language :: Python :: 3
License-File: LICENSE
